main.py
setup.py
dreamfusion.egg-info/PKG-INFO
dreamfusion.egg-info/SOURCES.txt
dreamfusion.egg-info/dependency_links.txt
dreamfusion.egg-info/requires.txt
dreamfusion.egg-info/top_level.txt